py_nvfan/__init__.py
py_nvfan/config.py
py_nvfan/nvidialib.py
py_nvfan-0.1.22.dist-info/METADATA
py_nvfan-0.1.22.dist-info/WHEEL
py_nvfan-0.1.22.dist-info/entry_points.txt
py_nvfan-0.1.22.dist-info/licenses/LICENSE
py_nvfan-0.1.22.dist-info/RECORD
