Metadata-Version: 2.4
Name: py-nvfan
Version: 0.1.22
Summary: Automatic Fan Control for NVIDIA Graphics Cards Based on Temperature.
Project-URL: homepage, https://github.com/AntraXClown/py-nvfan
Project-URL: Repository, https://github.com/AntraXClown/py-nvfan
Author-email: Antrax <fredcox@gmail.com>
License: MIT
License-File: LICENSE
Requires-Python: >=3.12
Requires-Dist: confz>=2.1.0
Requires-Dist: pynvml>=12.0.0
Requires-Dist: rich>=14.0.0
